__init__.py
calendar_calc.py
calendar_calc-0.1.dist-info/LICENSE
calendar_calc-0.1.dist-info/METADATA
calendar_calc-0.1.dist-info/WHEEL
calendar_calc-0.1.dist-info/top_level.txt
calendar_calc-0.1.dist-info/RECORD
